Metadata-Version: 2.1
Name: systembridgebackend
Version: 4.2.9
Summary: System Bridge Backend
Home-page: https://github.com/timmo001/system-bridge-backend
Author: Aidan Timson (Timmo)
Author-email: aidan@timmo.dev
License: Apache-2.0
Keywords: system-bridge
Requires-Python: >=3.11
License-File: LICENSE
Requires-Dist: aiofiles==24.1.0
Requires-Dist: aiohttp>=3.9.0b0
Requires-Dist: fastapi==0.112.1
Requires-Dist: incremental>=24.7.2
Requires-Dist: keyboard==0.13.5
Requires-Dist: mutagen==1.47.0
Requires-Dist: packaging>=24.0
Requires-Dist: plyer==2.1.0
Requires-Dist: psutil==6.0.0
Requires-Dist: python-multipart==0.0.9
Requires-Dist: screeninfo==0.8.1
Requires-Dist: systembridgeconnector==4.1.5
Requires-Dist: systembridgemodels==4.2.4
Requires-Dist: systembridgeshared==4.0.7
Requires-Dist: typer==0.12.3
Requires-Dist: uvicorn[standard]==0.30.6
Requires-Dist: zeroconf==0.132.2
